dejavu/__init__.py
dejavu/base_classes/__init__.py
dejavu/base_classes/base_database.py
dejavu/base_classes/base_recognizer.py
dejavu/base_classes/common_database.py
dejavu/config/__init__.py
dejavu/config/settings.py
dejavu/database_handler/__init__.py
dejavu/database_handler/mysql_database.py
dejavu/database_handler/postgres_database.py
dejavu/logic/__init__.py
dejavu/logic/decoder.py
dejavu/logic/fingerprint.py
dejavu/logic/recognizer/__init__.py
dejavu/logic/recognizer/file_recognizer.py
dejavu/logic/recognizer/microphone_recognizer.py
dejavu/tests/__init__.py
dejavu/tests/dejavu_test.py
dejavu/third_party/__init__.py
dejavu/third_party/wavio.py
PyDejavu_Rollong-0.1.6.dist-info/LICENSE.md
PyDejavu_Rollong-0.1.6.dist-info/METADATA
PyDejavu_Rollong-0.1.6.dist-info/WHEEL
PyDejavu_Rollong-0.1.6.dist-info/top_level.txt
PyDejavu_Rollong-0.1.6.dist-info/RECORD
